{"schemaVersion":"standard-doc-v2","source":{"path":"design-data/design-heros/敏捷/镜中人","extension":"","size":1909,"modifiedAt":"2026-06-18T10:32:05.333Z"},"meta":{"title":"镜中人","category":"hero","group":"英雄 / 敏捷","purpose":"英雄 / 敏捷 / 近战","attribute":"敏捷","hero":"镜中人"},"parser":{"contentType":"text","format":"structured-text","profile":"kv-text","lineCount":68,"fieldCount":33,"blockCount":40},"fields":{"攻击类型":"近战","攻击距离":"130","基础攻击间隔":"1.6","基础移动速度":"290","主属性":"敏捷","力量":"23 + 2","敏捷":"25 + 3.5","智力":"21 + 1.8","天生技能":"","反射":"卡加米受到的负面状态施法者也会同样受到，cd 15s","技能1":"倒影\n卡加米可以映射出目标单位的倒影，倒影无敌，获得移动速度提升，继承目标一定比例攻击力，\n会持续攻击该单位，直到消失或者目标死亡，倒影可以被弱驱散","施法距离":"500","攻击继承":"60%/70%/80%/90%","持续时间":["5","1.5/2/2.5/3","5/6.5/8"],"移速提高":"4%/7%/10%/13%","冷却":["25/23/21/19","30/27/24/21s","100/85/70"],"魔力消耗":["75","90","130"],"技能2":"潜镜\n卡加米进入无敌状态，移动速度降低，持续降低周围范围内单位的护甲，持续一段时间，该技能攻击后自动解除\n对非英雄单位效果减半","影响范围半径":"200","每0.5秒护甲降低":"1/1.5/2/2.5","移动速度降低":"50%/45%/40%/35%","护甲降低持续时间":"5s","技能3":"","心恐":"卡加米的每次攻击都会使猎物更加绝望胆寒，降低对方移动速度，\n可以叠加，每层持续5s，倒影继承该技能,可以被弱驱散","每层降低移速":"4%/5.5%/7%/8.5%","最高层数":"5","技能4":"化镜\n卡加米将自身镜面化，护甲，魔抗和伤害减免都归零，但是免疫异常状态和控制效果，生命值立刻充满，\n当此技能结束时如果卡加米未死亡，剩余生命将取施放之前和当前的最大值,此技能状态下仍然受到治疗","阳印":"","轻镜":"潜镜的速度损失-25%","阴印":"隐镜\n潜镜时同时处于隐身状态","铸魔":"倒影持续期间再次使用该技能，将自身和倒影换位","铸神":"心恐不可驱散，并且会减小目标移动速度抗性50%，\n移动速度抗性不会因此被降低到0一下","_header":"镜中人"},"sections":[{"key":"_header","value":"镜中人"},{"key":"段落","value":"镜中人\n卡加米"},{"key":"攻击类型","value":"近战"},{"key":"攻击距离","value":"130"},{"key":"基础攻击间隔","value":"1.6"},{"key":"基础移动速度","value":"290"},{"key":"主属性","value":"敏捷"},{"key":"力量","value":"23 + 2"},{"key":"敏捷","value":"25 + 3.5"},{"key":"智力","value":"21 + 1.8"},{"key":"天生技能","value":""},{"key":"反射","value":"卡加米受到的负面状态施法者也会同样受到，cd 15s"},{"key":"技能1","value":"倒影\n卡加米可以映射出目标单位的倒影，倒影无敌，获得移动速度提升，继承目标一定比例攻击力，\n会持续攻击该单位，直到消失或者目标死亡，倒影可以被弱驱散"},{"key":"施法距离","value":"500"},{"key":"攻击继承","value":"60%/70%/80%/90%"},{"key":"持续时间","value":"5"},{"key":"移速提高","value":"4%/7%/10%/13%"},{"key":"冷却","value":"25/23/21/19"},{"key":"魔力消耗","value":"75"},{"key":"技能2","value":"潜镜\n卡加米进入无敌状态，移动速度降低，持续降低周围范围内单位的护甲，持续一段时间，该技能攻击后自动解除\n对非英雄单位效果减半"},{"key":"影响范围半径","value":"200"},{"key":"持续时间","value":"1.5/2/2.5/3"},{"key":"每0.5秒护甲降低","value":"1/1.5/2/2.5"},{"key":"移动速度降低","value":"50%/45%/40%/35%"},{"key":"护甲降低持续时间","value":"5s"},{"key":"冷却","value":"30/27/24/21s"},{"key":"魔力消耗","value":"90"},{"key":"技能3","value":""},{"key":"心恐","value":"卡加米的每次攻击都会使猎物更加绝望胆寒，降低对方移动速度，\n可以叠加，每层持续5s，倒影继承该技能,可以被弱驱散"},{"key":"每层降低移速","value":"4%/5.5%/7%/8.5%"},{"key":"最高层数","value":"5"},{"key":"技能4","value":"化镜\n卡加米将自身镜面化，护甲，魔抗和伤害减免都归零，但是免疫异常状态和控制效果，生命值立刻充满，\n当此技能结束时如果卡加米未死亡，剩余生命将取施放之前和当前的最大值,此技能状态下仍然受到治疗"},{"key":"持续时间","value":"5/6.5/8"},{"key":"冷却","value":"100/85/70"},{"key":"魔力消耗","value":"130"},{"key":"阳印","value":""},{"key":"轻镜","value":"潜镜的速度损失-25%"},{"key":"阴印","value":"隐镜\n潜镜时同时处于隐身状态"},{"key":"铸魔","value":"倒影持续期间再次使用该技能，将自身和倒影换位"},{"key":"铸神","value":"心恐不可驱散，并且会减小目标移动速度抗性50%，\n移动速度抗性不会因此被降低到0一下"}],"blocks":[{"type":"heading","level":1,"title":"镜中人","anchor":"#镜中人"},{"type":"paragraph","text":"镜中人\n卡加米"},{"type":"kv","key":"攻击类型","value":"近战"},{"type":"kv","key":"攻击距离","value":"130"},{"type":"kv","key":"基础攻击间隔","value":"1.6"},{"type":"kv","key":"基础移动速度","value":"290"},{"type":"kv","key":"主属性","value":"敏捷"},{"type":"kv","key":"力量","value":"23 + 2"},{"type":"kv","key":"敏捷","value":"25 + 3.5"},{"type":"kv","key":"智力","value":"21 + 1.8"},{"type":"kv","key":"天生技能","value":""},{"type":"kv","key":"反射","value":"卡加米受到的负面状态施法者也会同样受到，cd 15s"},{"type":"kv","key":"技能1","value":"倒影\n卡加米可以映射出目标单位的倒影，倒影无敌，获得移动速度提升，继承目标一定比例攻击力，\n会持续攻击该单位，直到消失或者目标死亡，倒影可以被弱驱散"},{"type":"kv","key":"施法距离","value":"500"},{"type":"kv","key":"攻击继承","value":"60%/70%/80%/90%"},{"type":"kv","key":"持续时间","value":"5"},{"type":"kv","key":"移速提高","value":"4%/7%/10%/13%"},{"type":"kv","key":"冷却","value":"25/23/21/19"},{"type":"kv","key":"魔力消耗","value":"75"},{"type":"kv","key":"技能2","value":"潜镜\n卡加米进入无敌状态，移动速度降低，持续降低周围范围内单位的护甲，持续一段时间，该技能攻击后自动解除\n对非英雄单位效果减半"},{"type":"kv","key":"影响范围半径","value":"200"},{"type":"kv","key":"持续时间","value":"1.5/2/2.5/3"},{"type":"kv","key":"每0.5秒护甲降低","value":"1/1.5/2/2.5"},{"type":"kv","key":"移动速度降低","value":"50%/45%/40%/35%"},{"type":"kv","key":"护甲降低持续时间","value":"5s"},{"type":"kv","key":"冷却","value":"30/27/24/21s"},{"type":"kv","key":"魔力消耗","value":"90"},{"type":"kv","key":"技能3","value":""},{"type":"kv","key":"心恐","value":"卡加米的每次攻击都会使猎物更加绝望胆寒，降低对方移动速度，\n可以叠加，每层持续5s，倒影继承该技能,可以被弱驱散"},{"type":"kv","key":"每层降低移速","value":"4%/5.5%/7%/8.5%"},{"type":"kv","key":"最高层数","value":"5"},{"type":"kv","key":"技能4","value":"化镜\n卡加米将自身镜面化，护甲，魔抗和伤害减免都归零，但是免疫异常状态和控制效果，生命值立刻充满，\n当此技能结束时如果卡加米未死亡，剩余生命将取施放之前和当前的最大值,此技能状态下仍然受到治疗"},{"type":"kv","key":"持续时间","value":"5/6.5/8"},{"type":"kv","key":"冷却","value":"100/85/70"},{"type":"kv","key":"魔力消耗","value":"130"},{"type":"kv","key":"阳印","value":""},{"type":"kv","key":"轻镜","value":"潜镜的速度损失-25%"},{"type":"kv","key":"阴印","value":"隐镜\n潜镜时同时处于隐身状态"},{"type":"kv","key":"铸魔","value":"倒影持续期间再次使用该技能，将自身和倒影换位"},{"type":"kv","key":"铸神","value":"心恐不可驱散，并且会减小目标移动速度抗性50%，\n移动速度抗性不会因此被降低到0一下"}],"outline":[{"id":"镜中人","title":"镜中人","level":1,"anchor":"#镜中人","children":[]}],"parserStats":{"blockCount":40,"headingCount":1,"paragraphCount":1,"listCount":0,"tableCount":0,"kvCount":38},"rawPath":"design-data/design-heros/敏捷/镜中人","raw":"镜中人\n卡加米\n攻击类型：近战\n攻击距离：130\n基础攻击间隔：1.6\n基础移动速度：290\n主属性：敏捷\n力量：23 + 2\n敏捷：25 + 3.5\n智力：21 + 1.8\n\n天生技能：\n反射：\n卡加米受到的负面状态施法者也会同样受到，cd 15s\n\n技能1：\n倒影\n卡加米可以映射出目标单位的倒影，倒影无敌，获得移动速度提升，继承目标一定比例攻击力，\n会持续攻击该单位，直到消失或者目标死亡，倒影可以被弱驱散\n施法距离:500\n攻击继承:60%/70%/80%/90%\n持续时间:5\n移速提高:4%/7%/10%/13%\n冷却：25/23/21/19\n魔力消耗：75\n\n技能2：\n潜镜\n卡加米进入无敌状态，移动速度降低，持续降低周围范围内单位的护甲，持续一段时间，该技能攻击后自动解除\n对非英雄单位效果减半\n影响范围半径:200\n持续时间:1.5/2/2.5/3\n每0.5秒护甲降低:1/1.5/2/2.5\n移动速度降低:50%/45%/40%/35%\n护甲降低持续时间:5s\n冷却：30/27/24/21s\n魔力消耗：90\n\n技能3：\n心恐：\n卡加米的每次攻击都会使猎物更加绝望胆寒，降低对方移动速度，\n可以叠加，每层持续5s，倒影继承该技能,可以被弱驱散\n每层降低移速:4%/5.5%/7%/8.5%\n最高层数:5\n\n技能4：\n化镜\n卡加米将自身镜面化，护甲，魔抗和伤害减免都归零，但是免疫异常状态和控制效果，生命值立刻充满，\n当此技能结束时如果卡加米未死亡，剩余生命将取施放之前和当前的最大值,此技能状态下仍然受到治疗\n持续时间:5/6.5/8\n冷却：100/85/70\n魔力消耗：130\n\n阳印：\n轻镜：\n潜镜的速度损失-25%\n\n阴印：\n隐镜\n潜镜时同时处于隐身状态\n\n铸魔：\n倒影持续期间再次使用该技能，将自身和倒影换位\n\n铸神：\n心恐不可驱散，并且会减小目标移动速度抗性50%，\n移动速度抗性不会因此被降低到0一下\n"}
