{"schemaVersion":"standard-doc-v1","source":{"path":"design-data/design-heros/力量/火星异虫","extension":"","size":2052,"modifiedAt":"2026-06-18T10:32:05.324Z"},"meta":{"title":"火星异虫","category":"hero","group":"英雄 / 力量","attribute":"力量","hero":"火星异虫"},"parser":{"contentType":"text","format":"structured-text","lineCount":80},"fields":{"攻击类型":"远程","攻击距离":"300","基础攻击间隔":"1.7","基础移动速度":"310","主属性":"力量","力量":"25 + 3.6","敏捷":"18 + 1.7","智力":"22 + 2","天生技能":"腐蚀吐息\n马力克的攻击会降低对方的伤害减免\n不会降低到0以下","降低":"25+等级%","持续时间":["5s","5","4"],"技能1":"酸液攻击\n马力克的攻击附带酸液，酸液会造成持续\n纯粹伤害，并且叠加到一定的层数会发作\n沉默敌方单位，被沉默的单位不会再叠加\n并且层数重置到1","每秒伤害":["9/16/23/30","70/110/150"],"发作层数":"4","沉默时间":"0.8/1.2/1.6/2","技能2":"酸浪喷涌\n马力克向周围射出酸液，对周围造成魔法伤害\n如果目标处于沉默，则伤害类型为纯粹，每次\n受到攻击并且被命中都会降低该技能cd，cd不会低于2秒","范围":"400/425/450/475","伤害":"100/160/220/280","受击cd降低":"1","冷却":["18/16/14/12","90/80/70"],"魔力消耗":["80/90/100/110","100/120/140"],"技能3":"异虫甲壳\n马力克受到伤害之后，会有几率降低对方的攻击力\n每一层持续一段时间，该效果可以被弱驱散，叠满后\n新的层数会取代最早的层数","最高层数":"6","几率":"35%","每层攻击降低":"10/15/20/25","每层时间":"6","技能4":"神经毒素\n马力克向一个敌方单位注入神经毒素，该单位\n会持续受到魔法伤害，并且会陷入癫狂，无法攻击\n马力克之外的其他单位，该效果仅强驱散，如果目标死亡\n于该技能，则减少30s cd","最大施法距离":"400/500/600","阳印":"外星基因\n马力克受到毒素伤害时，移动速度会提高75","阴印":"硫化器官\n马力克受到驱散效果后，会立刻恢复150生命值","铸魔":"异虫甲壳还会降低技能伤害，\n每层4/5/6/7%","铸神":"神经毒素可以对自身释放，自身只受到50%伤害\n但是变成光环效果，范围内的敌方英雄不仅会\n受到伤害，而且只能攻击马力克","光环范围":"275","_header":"火星异虫\n马力克"},"sections":[{"key":"_header","value":"火星异虫\n马力克"},{"key":"攻击类型","value":"远程"},{"key":"攻击距离","value":"300"},{"key":"基础攻击间隔","value":"1.7"},{"key":"基础移动速度","value":"310"},{"key":"主属性","value":"力量"},{"key":"力量","value":"25 + 3.6"},{"key":"敏捷","value":"18 + 1.7"},{"key":"智力","value":"22 + 2"},{"key":"天生技能","value":"腐蚀吐息\n马力克的攻击会降低对方的伤害减免\n不会降低到0以下"},{"key":"降低","value":"25+等级%"},{"key":"持续时间","value":"5s"},{"key":"技能1","value":"酸液攻击\n马力克的攻击附带酸液，酸液会造成持续\n纯粹伤害，并且叠加到一定的层数会发作\n沉默敌方单位，被沉默的单位不会再叠加\n并且层数重置到1"},{"key":"每秒伤害","value":"9/16/23/30"},{"key":"持续时间","value":"5"},{"key":"发作层数","value":"4"},{"key":"沉默时间","value":"0.8/1.2/1.6/2"},{"key":"技能2","value":"酸浪喷涌\n马力克向周围射出酸液，对周围造成魔法伤害\n如果目标处于沉默，则伤害类型为纯粹，每次\n受到攻击并且被命中都会降低该技能cd，cd不会低于2秒"},{"key":"范围","value":"400/425/450/475"},{"key":"伤害","value":"100/160/220/280"},{"key":"受击cd降低","value":"1"},{"key":"冷却","value":"18/16/14/12"},{"key":"魔力消耗","value":"80/90/100/110"},{"key":"技能3","value":"异虫甲壳\n马力克受到伤害之后，会有几率降低对方的攻击力\n每一层持续一段时间，该效果可以被弱驱散，叠满后\n新的层数会取代最早的层数"},{"key":"最高层数","value":"6"},{"key":"几率","value":"35%"},{"key":"每层攻击降低","value":"10/15/20/25"},{"key":"每层时间","value":"6"},{"key":"技能4","value":"神经毒素\n马力克向一个敌方单位注入神经毒素，该单位\n会持续受到魔法伤害，并且会陷入癫狂，无法攻击\n马力克之外的其他单位，该效果仅强驱散，如果目标死亡\n于该技能，则减少30s cd"},{"key":"最大施法距离","value":"400/500/600"},{"key":"每秒伤害","value":"70/110/150"},{"key":"持续时间","value":"4"},{"key":"冷却","value":"90/80/70"},{"key":"魔力消耗","value":"100/120/140"},{"key":"阳印","value":"外星基因\n马力克受到毒素伤害时，移动速度会提高75"},{"key":"阴印","value":"硫化器官\n马力克受到驱散效果后，会立刻恢复150生命值"},{"key":"铸魔","value":"异虫甲壳还会降低技能伤害，\n每层4/5/6/7%"},{"key":"铸神","value":"神经毒素可以对自身释放，自身只受到50%伤害\n但是变成光环效果，范围内的敌方英雄不仅会\n受到伤害，而且只能攻击马力克"},{"key":"光环范围","value":"275"}],"rawPath":"design-data/design-heros/力量/火星异虫","raw":"火星异虫\n马力克\n攻击类型：远程\n攻击距离：300\n基础攻击间隔：1.7\n基础移动速度：310\n主属性：力量\n力量：25 + 3.6\n敏捷：18 + 1.7\n智力：22 + 2\n\n天生技能：\n腐蚀吐息\n马力克的攻击会降低对方的伤害减免\n不会降低到0以下\n降低：25+等级%\n持续时间：5s\n\n技能1：\n酸液攻击\n马力克的攻击附带酸液，酸液会造成持续\n纯粹伤害，并且叠加到一定的层数会发作\n沉默敌方单位，被沉默的单位不会再叠加\n并且层数重置到1\n每秒伤害：9/16/23/30\n持续时间：5\n发作层数：4\n沉默时间：0.8/1.2/1.6/2\n\n技能2：\n酸浪喷涌\n马力克向周围射出酸液，对周围造成魔法伤害\n如果目标处于沉默，则伤害类型为纯粹，每次\n受到攻击并且被命中都会降低该技能cd，cd不会低于2秒\n范围：400/425/450/475\n伤害：100/160/220/280\n受击cd降低：1\n冷却：18/16/14/12\n魔力消耗：80/90/100/110\n\n技能3：\n异虫甲壳\n马力克受到伤害之后，会有几率降低对方的攻击力\n每一层持续一段时间，该效果可以被弱驱散，叠满后\n新的层数会取代最早的层数\n最高层数：6\n几率：35%\n每层攻击降低：10/15/20/25\n每层时间：6\n\n技能4：\n神经毒素\n马力克向一个敌方单位注入神经毒素，该单位\n会持续受到魔法伤害，并且会陷入癫狂，无法攻击\n马力克之外的其他单位，该效果仅强驱散，如果目标死亡\n于该技能，则减少30s cd\n最大施法距离：400/500/600\n每秒伤害：70/110/150\n持续时间：4\n冷却：90/80/70\n魔力消耗：100/120/140\n\n阳印：\n外星基因\n马力克受到毒素伤害时，移动速度会提高75\n\n阴印：\n硫化器官\n马力克受到驱散效果后，会立刻恢复150生命值\n\n铸魔：\n异虫甲壳还会降低技能伤害，\n每层4/5/6/7%\n\n铸神：\n神经毒素可以对自身释放，自身只受到50%伤害\n但是变成光环效果，范围内的敌方英雄不仅会\n受到伤害，而且只能攻击马力克\n光环范围：275\n"}
