{"schemaVersion":"standard-doc-v2","source":{"path":"design-data/design-heros/力量/钢铁上将","extension":"","size":2351,"modifiedAt":"2026-07-23T10:26:19.380Z"},"meta":{"title":"钢铁上将","category":"hero","group":"英雄 / 力量","purpose":"英雄 / 力量 / 远程","attribute":"力量","hero":"钢铁上将","hasBackstory":true,"backstorySource":"design-data/backstory/力量/钢铁上将.txt"},"parser":{"contentType":"text","format":"structured-text","profile":"kv-text","lineCount":105,"fieldCount":20,"blockCount":21},"fields":{"别名":"希尔芙","英文名":"","攻击类型":"远程","攻击距离":"450","基础攻击间隔":"1.6","基础移动速度":"295","主属性":"力量","力量":"24 + 2.9","敏捷":"21 + 2.3","智力":"22 + 2.2","天生技能":"名称：士气提振\n类型：\n描述：希尔芙及其控制的单位的攻击速度提高10+希尔芙等级","技能1":"名称：金属控制\n类型：\n描述：希尔芙拥有操控金属的能力，缴械周围敌方单位\n可被弱驱散\n范围：300/350/400/450\n持续时间：2/2.5/3/3.5\n冷却：25/22/19/16\n魔力消耗：80/90/100/110","技能2":"名称：pks无人机\n类型：\n描述：希尔芙召唤无人机协助战斗，无人机拥有高空视野\n如果无人机未阵亡，再次使用会刷新无人机的生命值\n无人机属性\n攻击力：30/45/60/75\n攻击间隔：1.8/1.7/1.6/1.5\n生命值：600/800/1000/1200\n生命恢复：3/5/7/9\n护甲：1\n魔法抗性：10%\n攻击距离：500\n移动速度：350\n冷却：60/50/40/30\n魔力消耗：100","技能3":"名称：mat坦克\n类型：\n描述：希尔芙召唤坦克协助战斗，坦克拥有碾压伤害\n如果坦克未阵亡，在次使用会刷新坦克的生命值\n坦克属性\n攻击力：50/80/110/140\n攻击间隔：2\n生命值：800/1200/1600/2000\n生命恢复：4/7/10/13\n护甲：3/5/7/9\n魔法抗性：30%\n攻击距离：400\n移动速度：300/320/340/360\n碾压伤害：每秒对周围150码造成30/50/70/90魔法伤害\n冷却：45\n魔力消耗：100","技能4":"名称：钢铁洪流\n类型：\n描述：希尔芙及其控制的单位的移动速度大幅提高，\n并且免疫减速，获得额外攻击力，持续一段时间\n移动速度提高：50/85/120\n额外攻击力：20/35/50%\n持续时间：15\n冷却：120/100/80\n魔力消耗：120","阳印":"名称：工业链\n描述：mat坦克冷却时间-15","阴印":"名称：刺钉履带\n描述：mat坦克的碾压范围+100","铸魔":"名称：无人机拥有技能\n描述：\n自爆冲击：\n无人机向一点冲锋，对范围造成物理伤害和沉默\n并且立刻自毁\n距离：500\n冲锋速度：700\n范围：250\n伤害：200\n沉默时间：2s","铸神":"名称：\n描述：增加新技能\n阵地屏障\n在一个范围内布下阵地，范围内的友方单位的\n魔法抗性提高\n施法距离：400\n范围半径：300\n魔法抗性提高：35%\n持续时间：8\n冷却：35","_header":"钢铁上将"},"sections":[{"key":"_header","value":"钢铁上将"},{"key":"段落","value":"钢铁上将"},{"key":"别名","value":"希尔芙"},{"key":"英文名","value":""},{"key":"攻击类型","value":"远程"},{"key":"攻击距离","value":"450"},{"key":"基础攻击间隔","value":"1.6"},{"key":"基础移动速度","value":"295"},{"key":"主属性","value":"力量"},{"key":"力量","value":"24 + 2.9"},{"key":"敏捷","value":"21 + 2.3"},{"key":"智力","value":"22 + 2.2"},{"key":"天生技能","value":"名称：士气提振\n类型：\n描述：希尔芙及其控制的单位的攻击速度提高10+希尔芙等级"},{"key":"技能1","value":"名称：金属控制\n类型：\n描述：希尔芙拥有操控金属的能力，缴械周围敌方单位\n可被弱驱散\n范围：300/350/400/450\n持续时间：2/2.5/3/3.5\n冷却：25/22/19/16\n魔力消耗：80/90/100/110"},{"key":"技能2","value":"名称：pks无人机\n类型：\n描述：希尔芙召唤无人机协助战斗，无人机拥有高空视野\n如果无人机未阵亡，再次使用会刷新无人机的生命值\n无人机属性\n攻击力：30/45/60/75\n攻击间隔：1.8/1.7/1.6/1.5\n生命值：600/800/1000/1200\n生命恢复：3/5/7/9\n护甲：1\n魔法抗性：10%\n攻击距离：500\n移动速度：350\n冷却：60/50/40/30\n魔力消耗：100"},{"key":"技能3","value":"名称：mat坦克\n类型：\n描述：希尔芙召唤坦克协助战斗，坦克拥有碾压伤害\n如果坦克未阵亡，在次使用会刷新坦克的生命值\n坦克属性\n攻击力：50/80/110/140\n攻击间隔：2\n生命值：800/1200/1600/2000\n生命恢复：4/7/10/13\n护甲：3/5/7/9\n魔法抗性：30%\n攻击距离：400\n移动速度：300/320/340/360\n碾压伤害：每秒对周围150码造成30/50/70/90魔法伤害\n冷却：45\n魔力消耗：100"},{"key":"技能4","value":"名称：钢铁洪流\n类型：\n描述：希尔芙及其控制的单位的移动速度大幅提高，\n并且免疫减速，获得额外攻击力，持续一段时间\n移动速度提高：50/85/120\n额外攻击力：20/35/50%\n持续时间：15\n冷却：120/100/80\n魔力消耗：120"},{"key":"阳印","value":"名称：工业链\n描述：mat坦克冷却时间-15"},{"key":"阴印","value":"名称：刺钉履带\n描述：mat坦克的碾压范围+100"},{"key":"铸魔","value":"名称：无人机拥有技能\n描述：\n自爆冲击：\n无人机向一点冲锋，对范围造成物理伤害和沉默\n并且立刻自毁\n距离：500\n冲锋速度：700\n范围：250\n伤害：200\n沉默时间：2s"},{"key":"铸神","value":"名称：\n描述：增加新技能\n阵地屏障\n在一个范围内布下阵地，范围内的友方单位的\n魔法抗性提高\n施法距离：400\n范围半径：300\n魔法抗性提高：35%\n持续时间：8\n冷却：35"}],"blocks":[{"type":"heading","level":1,"title":"钢铁上将","anchor":"#钢铁上将"},{"type":"paragraph","text":"钢铁上将"},{"type":"kv","key":"别名","value":"希尔芙"},{"type":"kv","key":"英文名","value":""},{"type":"kv","key":"攻击类型","value":"远程"},{"type":"kv","key":"攻击距离","value":"450"},{"type":"kv","key":"基础攻击间隔","value":"1.6"},{"type":"kv","key":"基础移动速度","value":"295"},{"type":"kv","key":"主属性","value":"力量"},{"type":"kv","key":"力量","value":"24 + 2.9"},{"type":"kv","key":"敏捷","value":"21 + 2.3"},{"type":"kv","key":"智力","value":"22 + 2.2"},{"type":"kv","key":"天生技能","value":"名称：士气提振\n类型：\n描述：希尔芙及其控制的单位的攻击速度提高10+希尔芙等级"},{"type":"kv","key":"技能1","value":"名称：金属控制\n类型：\n描述：希尔芙拥有操控金属的能力，缴械周围敌方单位\n可被弱驱散\n范围：300/350/400/450\n持续时间：2/2.5/3/3.5\n冷却：25/22/19/16\n魔力消耗：80/90/100/110"},{"type":"kv","key":"技能2","value":"名称：pks无人机\n类型：\n描述：希尔芙召唤无人机协助战斗，无人机拥有高空视野\n如果无人机未阵亡，再次使用会刷新无人机的生命值\n无人机属性\n攻击力：30/45/60/75\n攻击间隔：1.8/1.7/1.6/1.5\n生命值：600/800/1000/1200\n生命恢复：3/5/7/9\n护甲：1\n魔法抗性：10%\n攻击距离：500\n移动速度：350\n冷却：60/50/40/30\n魔力消耗：100"},{"type":"kv","key":"技能3","value":"名称：mat坦克\n类型：\n描述：希尔芙召唤坦克协助战斗，坦克拥有碾压伤害\n如果坦克未阵亡，在次使用会刷新坦克的生命值\n坦克属性\n攻击力：50/80/110/140\n攻击间隔：2\n生命值：800/1200/1600/2000\n生命恢复：4/7/10/13\n护甲：3/5/7/9\n魔法抗性：30%\n攻击距离：400\n移动速度：300/320/340/360\n碾压伤害：每秒对周围150码造成30/50/70/90魔法伤害\n冷却：45\n魔力消耗：100"},{"type":"kv","key":"技能4","value":"名称：钢铁洪流\n类型：\n描述：希尔芙及其控制的单位的移动速度大幅提高，\n并且免疫减速，获得额外攻击力，持续一段时间\n移动速度提高：50/85/120\n额外攻击力：20/35/50%\n持续时间：15\n冷却：120/100/80\n魔力消耗：120"},{"type":"kv","key":"阳印","value":"名称：工业链\n描述：mat坦克冷却时间-15"},{"type":"kv","key":"阴印","value":"名称：刺钉履带\n描述：mat坦克的碾压范围+100"},{"type":"kv","key":"铸魔","value":"名称：无人机拥有技能\n描述：\n自爆冲击：\n无人机向一点冲锋，对范围造成物理伤害和沉默\n并且立刻自毁\n距离：500\n冲锋速度：700\n范围：250\n伤害：200\n沉默时间：2s"},{"type":"kv","key":"铸神","value":"名称：\n描述：增加新技能\n阵地屏障\n在一个范围内布下阵地，范围内的友方单位的\n魔法抗性提高\n施法距离：400\n范围半径：300\n魔法抗性提高：35%\n持续时间：8\n冷却：35"}],"outline":[{"id":"钢铁上将","title":"钢铁上将","level":1,"anchor":"#钢铁上将","children":[]}],"parserStats":{"blockCount":21,"headingCount":1,"paragraphCount":1,"listCount":0,"tableCount":0,"kvCount":19},"rawPath":"design-data/design-heros/力量/钢铁上将","raw":"钢铁上将\n别名：希尔芙\n英文名：\n攻击类型：远程\n攻击距离：450\n基础攻击间隔：1.6\n基础移动速度：295\n主属性：力量\n力量：24 + 2.9\n敏捷：21 + 2.3\n智力：22 + 2.2\n\n天生技能：\n名称：士气提振\n类型：\n描述：希尔芙及其控制的单位的攻击速度提高10+希尔芙等级\n\n技能1：\n名称：金属控制\n类型：\n描述：希尔芙拥有操控金属的能力，缴械周围敌方单位\n可被弱驱散\n范围：300/350/400/450\n持续时间：2/2.5/3/3.5\n冷却：25/22/19/16\n魔力消耗：80/90/100/110\n\n技能2：\n名称：pks无人机\n类型：\n描述：希尔芙召唤无人机协助战斗，无人机拥有高空视野\n如果无人机未阵亡，再次使用会刷新无人机的生命值\n无人机属性\n攻击力：30/45/60/75\n攻击间隔：1.8/1.7/1.6/1.5\n生命值：600/800/1000/1200\n生命恢复：3/5/7/9\n护甲：1\n魔法抗性：10%\n攻击距离：500\n移动速度：350\n冷却：60/50/40/30\n魔力消耗：100\n\n技能3：\n名称：mat坦克\n类型：\n描述：希尔芙召唤坦克协助战斗，坦克拥有碾压伤害\n如果坦克未阵亡，在次使用会刷新坦克的生命值\n坦克属性\n攻击力：50/80/110/140\n攻击间隔：2\n生命值：800/1200/1600/2000\n生命恢复：4/7/10/13\n护甲：3/5/7/9\n魔法抗性：30%\n攻击距离：400\n移动速度：300/320/340/360\n碾压伤害：每秒对周围150码造成30/50/70/90魔法伤害\n冷却：45\n魔力消耗：100\n\n技能4：\n名称：钢铁洪流\n类型：\n描述：希尔芙及其控制的单位的移动速度大幅提高，\n并且免疫减速，获得额外攻击力，持续一段时间\n移动速度提高：50/85/120\n额外攻击力：20/35/50%\n持续时间：15\n冷却：120/100/80\n魔力消耗：120\n\n阳印：\n名称：工业链\n描述：mat坦克冷却时间-15\n\n阴印：\n名称：刺钉履带\n描述：mat坦克的碾压范围+100\n\n铸魔：\n名称：无人机拥有技能\n描述：\n自爆冲击：\n无人机向一点冲锋，对范围造成物理伤害和沉默\n并且立刻自毁\n距离：500\n冲锋速度：700\n范围：250\n伤害：200\n沉默时间：2s\n\n铸神：\n名称：\n描述：增加新技能\n阵地屏障\n在一个范围内布下阵地，范围内的友方单位的\n魔法抗性提高\n施法距离：400\n范围半径：300\n魔法抗性提高：35%\n持续时间：8\n冷却：35\n","backstory":{"source":"design-data/backstory/力量/钢铁上将.txt","category":"backstory","group":"背景故事 / 力量","title":"在钢铁与火焰彼此吞噬的年代，","purpose":"背景故事 / 力量","meta":{"title":"在钢铁与火焰彼此吞噬的年代，","category":"backstory","group":"背景故事 / 力量","purpose":"背景故事 / 力量","attribute":"力量","hero":"钢铁上将"},"fields":{"士兵们私下说":"“上将还在，\n枪就不会卡壳。”","有人说":"“一辆坦克是兵器。\n希尔芙的坦克，是军团。”","_header":"在钢铁与火焰彼此吞噬的年代，"},"sections":[{"key":"_header","value":"在钢铁与火焰彼此吞噬的年代，"},{"key":"段落","value":"在钢铁与火焰彼此吞噬的年代，\n在帝国最混乱、最危急、最没有退路的战场上，\n总有一个身影站在最前线。"},{"key":"段落","value":"她不高呼口号，\n不需要誓言，\n甚至不必回头确认。"},{"key":"段落","value":"因为只要她站在那里，\n战线就不会后退。"},{"key":"段落","value":"她的名字，\n在军工厂的警报声里被反复校准，\n在前线壕沟的无线电中被低声确认，\n在装甲履带启动的瞬间被引擎记住——"},{"key":"段落","value":"钢铁上将 · 希尔芙。"},{"key":"段落","value":"她出生的那一年，\n帝国北境正被机兽洪潮撕裂。\n战线崩塌，\n首都震动，\n钢铁城市像被野兽啃噬的骨架。"},{"key":"段落","value":"而就在那个夜晚，\n当她第一次哭出声来，\n军工厂里停滞的仪表重新归零，\n卡死的齿轮开始转动，\n前线通讯中的杂音诡异地下降。"},{"key":"段落","value":"有人说这是巧合。\n但参谋部知道——\n那是“操控金属者”的血脉在呼吸。"},{"key":"段落","value":"希尔芙自幼便能听见机械。\n不是声音，\n而是节奏。"},{"key":"段落","value":"她知道哪一枚齿轮即将失衡，\n哪一根传动轴会在三分钟后断裂，\n哪一台武器在下一次射击时会迟疑半拍。"},{"key":"段落","value":"她走上军旅之路，\n不靠门第，\n不靠荣耀，\n只靠一种无法复制的事实——"},{"key":"段落","value":"只要她站在战场上，\n军心就会稳定。\n士兵的手会更快，\n武器的节奏会更顺，\n攻击仿佛被无形之力推动。"},{"key":"士兵们私下说","value":"“上将还在，\n枪就不会卡壳。”"},{"key":"段落","value":"当敌军逼近时，\n她只需抬手。"},{"key":"段落","value":"空气中的金属微粒开始震颤，\n共鸣扩散，\n意志被夺走。"},{"key":"段落","value":"敌人的刀刃变得沉重，\n枪械像失去灵魂般脱手，\n铠甲锁死，\n关节僵住。"},{"key":"段落","value":"不是魔法，\n是命令。"},{"key":"段落","value":"金属控制之下，\n敌军被迫跪伏，\n仿佛整个战场都听懂了她的意志。"},{"key":"段落","value":"但真正让帝国稳住崩溃边缘的，\n不是她的个人力量，\n而是她的军团。"},{"key":"段落","value":"第一批升空的，\n是 pks 无人机。\n它们盘旋在空中，\n像冷静的眼睛，\n标记、校准、覆盖火力。"},{"key":"段落","value":"只要无人机尚有残骸，\n希尔芙一句命令，\n它们就能重组、复位、重返战斗，\n连异常状态都会被强制抹除。"},{"key":"段落","value":"随后登场的，\n是 mat 坦克。"},{"key":"段落","value":"那不是载具，\n是移动的战线。"},{"key":"段落","value":"履带碾碎地形，\n炮火重塑视野，\n靠近它的敌人\n会在金属与重量中消失。"},{"key":"有人说","value":"“一辆坦克是兵器。\n希尔芙的坦克，是军团。”"},{"key":"段落","value":"而当她真正举起指挥旗，\n钢铁洪流便开始流动。"},{"key":"段落","value":"所有机械同时轰鸣，\n士兵的步伐加快，\n武器的火力被推至极限，\n减速、泥泞、压制\n在那一刻失去意义。"},{"key":"段落","value":"那不是进攻，\n是推进。"},{"key":"段落","value":"不是军队，\n是压路机。"},{"key":"段落","value":"后来，无人机学会自爆，\n在敌阵中绽放成沉默与毁灭。\n坦克的履带加装刺钉，\n碾压范围不断扩大。"},{"key":"段落","value":"当敌方法师抬手施法，\n阵地忽然亮起冷金色的光。"},{"key":"段落","value":"那是阵地屏障。"},{"key":"段落","value":"金属旗帜扎入大地，\n魔法在其上崩解，\n友军的防线如同焊死的钢板。"},{"key":"段落","value":"希尔芙从不咆哮。\n她没有华丽的光。\n她甚至不需要被看见。"},{"key":"段落","value":"但她比任何英雄都可怕。"},{"key":"段落","value":"因为她的背后，\n是工业、纪律、军团、机械、火焰、\n以及不会停下的未来。"},{"key":"段落","value":"当敌人听见履带震动，\n听见金属共鸣，\n他们就会明白——"},{"key":"段落","value":"她来了。"},{"key":"段落","value":"钢铁上将 · 希尔芙。\n她向前一步，\n整条战线随之推进。"}],"outline":[{"id":"在钢铁与火焰彼此吞噬的年代","title":"在钢铁与火焰彼此吞噬的年代，","level":1,"anchor":"#在钢铁与火焰彼此吞噬的年代","children":[]}],"blocks":[{"type":"heading","level":1,"title":"在钢铁与火焰彼此吞噬的年代，","anchor":"#在钢铁与火焰彼此吞噬的年代"},{"type":"paragraph","text":"在钢铁与火焰彼此吞噬的年代，\n在帝国最混乱、最危急、最没有退路的战场上，\n总有一个身影站在最前线。"},{"type":"paragraph","text":"她不高呼口号，\n不需要誓言，\n甚至不必回头确认。"},{"type":"paragraph","text":"因为只要她站在那里，\n战线就不会后退。"},{"type":"paragraph","text":"她的名字，\n在军工厂的警报声里被反复校准，\n在前线壕沟的无线电中被低声确认，\n在装甲履带启动的瞬间被引擎记住——"},{"type":"paragraph","text":"钢铁上将 · 希尔芙。"},{"type":"paragraph","text":"她出生的那一年，\n帝国北境正被机兽洪潮撕裂。\n战线崩塌，\n首都震动，\n钢铁城市像被野兽啃噬的骨架。"},{"type":"paragraph","text":"而就在那个夜晚，\n当她第一次哭出声来，\n军工厂里停滞的仪表重新归零，\n卡死的齿轮开始转动，\n前线通讯中的杂音诡异地下降。"},{"type":"paragraph","text":"有人说这是巧合。\n但参谋部知道——\n那是“操控金属者”的血脉在呼吸。"},{"type":"paragraph","text":"希尔芙自幼便能听见机械。\n不是声音，\n而是节奏。"},{"type":"paragraph","text":"她知道哪一枚齿轮即将失衡，\n哪一根传动轴会在三分钟后断裂，\n哪一台武器在下一次射击时会迟疑半拍。"},{"type":"paragraph","text":"她走上军旅之路，\n不靠门第，\n不靠荣耀，\n只靠一种无法复制的事实——"},{"type":"paragraph","text":"只要她站在战场上，\n军心就会稳定。\n士兵的手会更快，\n武器的节奏会更顺，\n攻击仿佛被无形之力推动。"},{"type":"kv","key":"士兵们私下说","value":"“上将还在，\n枪就不会卡壳。”"},{"type":"paragraph","text":"当敌军逼近时，\n她只需抬手。"},{"type":"paragraph","text":"空气中的金属微粒开始震颤，\n共鸣扩散，\n意志被夺走。"},{"type":"paragraph","text":"敌人的刀刃变得沉重，\n枪械像失去灵魂般脱手，\n铠甲锁死，\n关节僵住。"},{"type":"paragraph","text":"不是魔法，\n是命令。"},{"type":"paragraph","text":"金属控制之下，\n敌军被迫跪伏，\n仿佛整个战场都听懂了她的意志。"},{"type":"paragraph","text":"但真正让帝国稳住崩溃边缘的，\n不是她的个人力量，\n而是她的军团。"},{"type":"paragraph","text":"第一批升空的，\n是 pks 无人机。\n它们盘旋在空中，\n像冷静的眼睛，\n标记、校准、覆盖火力。"},{"type":"paragraph","text":"只要无人机尚有残骸，\n希尔芙一句命令，\n它们就能重组、复位、重返战斗，\n连异常状态都会被强制抹除。"},{"type":"paragraph","text":"随后登场的，\n是 mat 坦克。"},{"type":"paragraph","text":"那不是载具，\n是移动的战线。"},{"type":"paragraph","text":"履带碾碎地形，\n炮火重塑视野，\n靠近它的敌人\n会在金属与重量中消失。"},{"type":"kv","key":"有人说","value":"“一辆坦克是兵器。\n希尔芙的坦克，是军团。”"},{"type":"paragraph","text":"而当她真正举起指挥旗，\n钢铁洪流便开始流动。"},{"type":"paragraph","text":"所有机械同时轰鸣，\n士兵的步伐加快，\n武器的火力被推至极限，\n减速、泥泞、压制\n在那一刻失去意义。"},{"type":"paragraph","text":"那不是进攻，\n是推进。"},{"type":"paragraph","text":"不是军队，\n是压路机。"},{"type":"paragraph","text":"后来，无人机学会自爆，\n在敌阵中绽放成沉默与毁灭。\n坦克的履带加装刺钉，\n碾压范围不断扩大。"},{"type":"paragraph","text":"当敌方法师抬手施法，\n阵地忽然亮起冷金色的光。"},{"type":"paragraph","text":"那是阵地屏障。"},{"type":"paragraph","text":"金属旗帜扎入大地，\n魔法在其上崩解，\n友军的防线如同焊死的钢板。"},{"type":"paragraph","text":"希尔芙从不咆哮。\n她没有华丽的光。\n她甚至不需要被看见。"},{"type":"paragraph","text":"但她比任何英雄都可怕。"},{"type":"paragraph","text":"因为她的背后，\n是工业、纪律、军团、机械、火焰、\n以及不会停下的未来。"},{"type":"paragraph","text":"当敌人听见履带震动，\n听见金属共鸣，\n他们就会明白——"},{"type":"paragraph","text":"她来了。"},{"type":"paragraph","text":"钢铁上将 · 希尔芙。\n她向前一步，\n整条战线随之推进。"}],"parser":{"contentType":"text","format":"structured-text","profile":"kv-text","lineCount":155,"fieldCount":3,"blockCount":40},"parserStats":{"blockCount":40,"headingCount":1,"paragraphCount":37,"listCount":0,"tableCount":0,"kvCount":2},"rawPath":"design-data/backstory/力量/钢铁上将.txt","raw":"在钢铁与火焰彼此吞噬的年代，\n在帝国最混乱、最危急、最没有退路的战场上，\n总有一个身影站在最前线。\n\n她不高呼口号，\n不需要誓言，\n甚至不必回头确认。\n\n因为只要她站在那里，\n战线就不会后退。\n\n她的名字，\n在军工厂的警报声里被反复校准，\n在前线壕沟的无线电中被低声确认，\n在装甲履带启动的瞬间被引擎记住——\n\n钢铁上将 · 希尔芙。\n\n她出生的那一年，\n帝国北境正被机兽洪潮撕裂。\n战线崩塌，\n首都震动，\n钢铁城市像被野兽啃噬的骨架。\n\n而就在那个夜晚，\n当她第一次哭出声来，\n军工厂里停滞的仪表重新归零，\n卡死的齿轮开始转动，\n前线通讯中的杂音诡异地下降。\n\n有人说这是巧合。\n但参谋部知道——\n那是“操控金属者”的血脉在呼吸。\n\n希尔芙自幼便能听见机械。\n不是声音，\n而是节奏。\n\n她知道哪一枚齿轮即将失衡，\n哪一根传动轴会在三分钟后断裂，\n哪一台武器在下一次射击时会迟疑半拍。\n\n她走上军旅之路，\n不靠门第，\n不靠荣耀，\n只靠一种无法复制的事实——\n\n只要她站在战场上，\n军心就会稳定。\n士兵的手会更快，\n武器的节奏会更顺，\n攻击仿佛被无形之力推动。\n\n士兵们私下说：\n“上将还在，\n枪就不会卡壳。”\n\n当敌军逼近时，\n她只需抬手。\n\n空气中的金属微粒开始震颤，\n共鸣扩散，\n意志被夺走。\n\n敌人的刀刃变得沉重，\n枪械像失去灵魂般脱手，\n铠甲锁死，\n关节僵住。\n\n不是魔法，\n是命令。\n\n金属控制之下，\n敌军被迫跪伏，\n仿佛整个战场都听懂了她的意志。\n\n但真正让帝国稳住崩溃边缘的，\n不是她的个人力量，\n而是她的军团。\n\n第一批升空的，\n是 pks 无人机。\n它们盘旋在空中，\n像冷静的眼睛，\n标记、校准、覆盖火力。\n\n只要无人机尚有残骸，\n希尔芙一句命令，\n它们就能重组、复位、重返战斗，\n连异常状态都会被强制抹除。\n\n随后登场的，\n是 mat 坦克。\n\n那不是载具，\n是移动的战线。\n\n履带碾碎地形，\n炮火重塑视野，\n靠近它的敌人\n会在金属与重量中消失。\n\n有人说：\n“一辆坦克是兵器。\n希尔芙的坦克，是军团。”\n\n而当她真正举起指挥旗，\n钢铁洪流便开始流动。\n\n所有机械同时轰鸣，\n士兵的步伐加快，\n武器的火力被推至极限，\n减速、泥泞、压制\n在那一刻失去意义。\n\n那不是进攻，\n是推进。\n\n不是军队，\n是压路机。\n\n后来，无人机学会自爆，\n在敌阵中绽放成沉默与毁灭。\n坦克的履带加装刺钉，\n碾压范围不断扩大。\n\n当敌方法师抬手施法，\n阵地忽然亮起冷金色的光。\n\n那是阵地屏障。\n\n金属旗帜扎入大地，\n魔法在其上崩解，\n友军的防线如同焊死的钢板。\n\n希尔芙从不咆哮。\n她没有华丽的光。\n她甚至不需要被看见。\n\n但她比任何英雄都可怕。\n\n因为她的背后，\n是工业、纪律、军团、机械、火焰、\n以及不会停下的未来。\n\n当敌人听见履带震动，\n听见金属共鸣，\n他们就会明白——\n\n她来了。\n\n钢铁上将 · 希尔芙。\n她向前一步，\n整条战线随之推进。\n"}}
