{"schemaVersion":"standard-doc-v2","source":{"path":"design-data/design-heros/智力/烈焰法皇","extension":"","size":1712,"modifiedAt":"2026-06-18T10:32:05.339Z"},"meta":{"title":"烈焰法皇","category":"hero","group":"英雄 / 智力","purpose":"英雄 / 智力 / 远程","attribute":"智力","hero":"烈焰法皇","hasBackstory":true,"backstorySource":"design-data/backstory/智力/烈焰法皇.txt"},"parser":{"contentType":"text","format":"structured-text","profile":"kv-text","lineCount":74,"fieldCount":25,"blockCount":26},"fields":{"攻击类型":"远程","攻击距离":"500","基础攻击间隔":"1.6","基础移动速度":"310","主属性":"智力","力量":"21 + 2.3","敏捷":"20 + 1.8","智力":"25 + 3.2","天生技能":"抗法面纱\n布尔玛受到的任何魔法伤害-(5+等级点)","技能1":"三昧真火\n布尔玛向前持续喷射三昧真火，造成魔法伤害，\n持续时间可以移动，不可被打断，可以转向","距离":"400","伤害宽度":"200","伤害间隔":"0.3","持续时间":"3","伤害":"12/20/28/36","冷却":"20/16/12/8","魔力消耗":"90/100/110/120","技能2":"地火焚原\n布尔玛从地底召唤火柱，对目标范围造成灼烧效果和减速\n范围半径：175\n施法距离：500/550/600/650\n灼烧持续时间：7\n灼烧每秒魔法伤害：20/30/40/50\n减速：20%\n减速持续时间：3\n冷却：18/16/14/12\n魔力消耗：100/105/110/115","技能3":"真炎法皇\n布尔玛有一定几率造成1.6倍魔法伤害，\n该效果每1秒最多触发一次，不受到冷却缩减影响\n几率：14/22/30/38%","技能4":"天火灭尽\n布尔码召唤天火，轰击目标单位，造成魔法伤害和眩晕\n该技能可以蓄力，蓄力需要原地持续施法，可以被打断，\n蓄力时间越长伤害越高\n施法距离：1000\n最长蓄力：4s\n每秒蓄力伤害提高：100/130/160\n眩晕：1/1.5/2s\n冷却：80/70/60\n魔力消耗：150/180/210","阳印":"邪火\n真炎法皇触发后会降低对方10%魔法抗性持续2s，可驱散","阴印":"火魔\n布尔玛的攻击的50%转换为魔法伤害","铸魔":"地火焚原的灼烧伤害不可以被驱散，而且cd-4s","铸神":"天火灭尽蓄力持续施法时可以移动，而且如果敌方英雄\n死于该技能，则立刻减少25scd","_header":"烈焰法皇"},"sections":[{"key":"_header","value":"烈焰法皇"},{"key":"段落","value":"烈焰法皇\n布尔玛"},{"key":"攻击类型","value":"远程"},{"key":"攻击距离","value":"500"},{"key":"基础攻击间隔","value":"1.6"},{"key":"基础移动速度","value":"310"},{"key":"主属性","value":"智力"},{"key":"力量","value":"21 + 2.3"},{"key":"敏捷","value":"20 + 1.8"},{"key":"智力","value":"25 + 3.2"},{"key":"天生技能","value":"抗法面纱\n布尔玛受到的任何魔法伤害-(5+等级点)"},{"key":"技能1","value":"三昧真火\n布尔玛向前持续喷射三昧真火，造成魔法伤害，\n持续时间可以移动，不可被打断，可以转向"},{"key":"距离","value":"400"},{"key":"伤害宽度","value":"200"},{"key":"伤害间隔","value":"0.3"},{"key":"持续时间","value":"3"},{"key":"伤害","value":"12/20/28/36"},{"key":"冷却","value":"20/16/12/8"},{"key":"魔力消耗","value":"90/100/110/120"},{"key":"技能2","value":"地火焚原\n布尔玛从地底召唤火柱，对目标范围造成灼烧效果和减速\n范围半径：175\n施法距离：500/550/600/650\n灼烧持续时间：7\n灼烧每秒魔法伤害：20/30/40/50\n减速：20%\n减速持续时间：3\n冷却：18/16/14/12\n魔力消耗：100/105/110/115"},{"key":"技能3","value":"真炎法皇\n布尔玛有一定几率造成1.6倍魔法伤害，\n该效果每1秒最多触发一次，不受到冷却缩减影响\n几率：14/22/30/38%"},{"key":"技能4","value":"天火灭尽\n布尔码召唤天火，轰击目标单位，造成魔法伤害和眩晕\n该技能可以蓄力，蓄力需要原地持续施法，可以被打断，\n蓄力时间越长伤害越高\n施法距离：1000\n最长蓄力：4s\n每秒蓄力伤害提高：100/130/160\n眩晕：1/1.5/2s\n冷却：80/70/60\n魔力消耗：150/180/210"},{"key":"阳印","value":"邪火\n真炎法皇触发后会降低对方10%魔法抗性持续2s，可驱散"},{"key":"阴印","value":"火魔\n布尔玛的攻击的50%转换为魔法伤害"},{"key":"铸魔","value":"地火焚原的灼烧伤害不可以被驱散，而且cd-4s"},{"key":"铸神","value":"天火灭尽蓄力持续施法时可以移动，而且如果敌方英雄\n死于该技能，则立刻减少25scd"}],"blocks":[{"type":"heading","level":1,"title":"烈焰法皇","anchor":"#烈焰法皇"},{"type":"paragraph","text":"烈焰法皇\n布尔玛"},{"type":"kv","key":"攻击类型","value":"远程"},{"type":"kv","key":"攻击距离","value":"500"},{"type":"kv","key":"基础攻击间隔","value":"1.6"},{"type":"kv","key":"基础移动速度","value":"310"},{"type":"kv","key":"主属性","value":"智力"},{"type":"kv","key":"力量","value":"21 + 2.3"},{"type":"kv","key":"敏捷","value":"20 + 1.8"},{"type":"kv","key":"智力","value":"25 + 3.2"},{"type":"kv","key":"天生技能","value":"抗法面纱\n布尔玛受到的任何魔法伤害-(5+等级点)"},{"type":"kv","key":"技能1","value":"三昧真火\n布尔玛向前持续喷射三昧真火，造成魔法伤害，\n持续时间可以移动，不可被打断，可以转向"},{"type":"kv","key":"距离","value":"400"},{"type":"kv","key":"伤害宽度","value":"200"},{"type":"kv","key":"伤害间隔","value":"0.3"},{"type":"kv","key":"持续时间","value":"3"},{"type":"kv","key":"伤害","value":"12/20/28/36"},{"type":"kv","key":"冷却","value":"20/16/12/8"},{"type":"kv","key":"魔力消耗","value":"90/100/110/120"},{"type":"kv","key":"技能2","value":"地火焚原\n布尔玛从地底召唤火柱，对目标范围造成灼烧效果和减速\n范围半径：175\n施法距离：500/550/600/650\n灼烧持续时间：7\n灼烧每秒魔法伤害：20/30/40/50\n减速：20%\n减速持续时间：3\n冷却：18/16/14/12\n魔力消耗：100/105/110/115"},{"type":"kv","key":"技能3","value":"真炎法皇\n布尔玛有一定几率造成1.6倍魔法伤害，\n该效果每1秒最多触发一次，不受到冷却缩减影响\n几率：14/22/30/38%"},{"type":"kv","key":"技能4","value":"天火灭尽\n布尔码召唤天火，轰击目标单位，造成魔法伤害和眩晕\n该技能可以蓄力，蓄力需要原地持续施法，可以被打断，\n蓄力时间越长伤害越高\n施法距离：1000\n最长蓄力：4s\n每秒蓄力伤害提高：100/130/160\n眩晕：1/1.5/2s\n冷却：80/70/60\n魔力消耗：150/180/210"},{"type":"kv","key":"阳印","value":"邪火\n真炎法皇触发后会降低对方10%魔法抗性持续2s，可驱散"},{"type":"kv","key":"阴印","value":"火魔\n布尔玛的攻击的50%转换为魔法伤害"},{"type":"kv","key":"铸魔","value":"地火焚原的灼烧伤害不可以被驱散，而且cd-4s"},{"type":"kv","key":"铸神","value":"天火灭尽蓄力持续施法时可以移动，而且如果敌方英雄\n死于该技能，则立刻减少25scd"}],"outline":[{"id":"烈焰法皇","title":"烈焰法皇","level":1,"anchor":"#烈焰法皇","children":[]}],"parserStats":{"blockCount":26,"headingCount":1,"paragraphCount":1,"listCount":0,"tableCount":0,"kvCount":24},"rawPath":"design-data/design-heros/智力/烈焰法皇","raw":"烈焰法皇\n布尔玛\n攻击类型：远程\n攻击距离：500\n基础攻击间隔：1.6\n基础移动速度：310\n主属性：智力\n力量：21 + 2.3\n敏捷：20 + 1.8\n智力：25 + 3.2\n\n天生技能：\n抗法面纱\n布尔玛受到的任何魔法伤害-(5+等级点)\n\n技能1：\n三昧真火\n布尔玛向前持续喷射三昧真火，造成魔法伤害，\n持续时间可以移动，不可被打断，可以转向\n\n距离:400\n伤害宽度：200\n伤害间隔：0.3\n持续时间：3\n伤害：12/20/28/36\n\n冷却：20/16/12/8\n魔力消耗：90/100/110/120\n\n技能2：\n地火焚原\n布尔玛从地底召唤火柱，对目标范围造成灼烧效果和减速\n范围半径：175\n施法距离：500/550/600/650\n灼烧持续时间：7\n灼烧每秒魔法伤害：20/30/40/50\n减速：20%\n减速持续时间：3\n冷却：18/16/14/12\n魔力消耗：100/105/110/115\n\n技能3：\n真炎法皇\n布尔玛有一定几率造成1.6倍魔法伤害，\n该效果每1秒最多触发一次，不受到冷却缩减影响\n几率：14/22/30/38%\n\n技能4：\n天火灭尽\n布尔码召唤天火，轰击目标单位，造成魔法伤害和眩晕\n该技能可以蓄力，蓄力需要原地持续施法，可以被打断，\n蓄力时间越长伤害越高\n施法距离：1000\n最长蓄力：4s\n每秒蓄力伤害提高：100/130/160\n眩晕：1/1.5/2s\n冷却：80/70/60\n魔力消耗：150/180/210\n\n阳印：\n邪火\n真炎法皇触发后会降低对方10%魔法抗性持续2s，可驱散\n\n阴印：\n火魔\n布尔玛的攻击的50%转换为魔法伤害\n\n铸魔：\n地火焚原的灼烧伤害不可以被驱散，而且cd-4s\n\n铸神：\n天火灭尽蓄力持续施法时可以移动，而且如果敌方英雄\n死于该技能，则立刻减少25scd\n","backstory":{"source":"design-data/backstory/智力/烈焰法皇.txt","category":"backstory","group":"背景故事 / 智力","title":"在火尚未学会燃烧的年代，","purpose":"背景故事 / 智力","meta":{"title":"在火尚未学会燃烧的年代，","category":"backstory","group":"背景故事 / 智力","purpose":"背景故事 / 智力","attribute":"智力","hero":"烈焰法皇"},"fields":{"都会明白":"","_header":"在火尚未学会燃烧的年代，"},"sections":[{"key":"_header","value":"在火尚未学会燃烧的年代，"},{"key":"段落","value":"在火尚未学会燃烧的年代，\n世界第一次听见了热的声音。"},{"key":"段落","value":"那声音化作一束光，\n那光化作一团火，\n那火最终化作一位皇者。"},{"key":"段落","value":"他的名号——\n布尔玛。"},{"key":"段落","value":"他行走，\n空气开始枯萎。"},{"key":"段落","value":"他驻足，\n阴影被瞬间蒸发。"},{"key":"段落","value":"魔法触及他，\n不是打中，\n是被烤成灰。"},{"key":"段落","value":"那是抗法面纱的呼吸。\n火焰为他守卫，\n火焰以他为尊。"},{"key":"段落","value":"布尔玛喷吐三昧真火，\n不是法术，\n是审判。"},{"key":"段落","value":"火焰倾泻成河，\n天地被他随意雕刻，\n敌人像纸张般卷曲、\n撕裂、\n化尽。"},{"key":"段落","value":"大地被他唤醒，\n地火从深处冲破枷锁，\n如怒吼，\n如惩戒，\n如大地自己选择的报复。"},{"key":"段落","value":"灼烧会追击敌人，\n像一段无法熄灭的罪行记录。"},{"key":"段落","value":"而当真炎法皇的光辉绽开，\n火焰在他手中狂舞，\n伤害成倍暴涨，\n连魔抗都会被烧穿，\n只留下焦黑与尖叫。"},{"key":"段落","value":"可这仍不是他的极致。"},{"key":"段落","value":"当布尔玛抬头望向天穹，\n连星辰都仿佛屏息，\n等待命运的指令。"},{"key":"段落","value":"他的手指落下——\n天火撕裂云层，\n轰鸣如破碎的宇宙，\n光芒像一次世界性的赎罪。"},{"key":"段落","value":"蓄力越久，\n天火越像神祇的怒目。"},{"key":"段落","value":"当火球砸落，\n敌人不知是生被夺走，\n还是灵被燃尽。"},{"key":"段落","value":"他站在烈焰中，\n像君王，\n像灾难，\n像火焰本身的意识在世界上行走。"},{"key":"段落","value":"布尔玛不需要宣告。\n凡目见其焰者，"},{"key":"都会明白","value":""},{"key":"段落","value":"——火焰有了意志。\n——意志选择了皇。\n——皇降临之处，万物终将以灰烬偿还。"}],"outline":[{"id":"在火尚未学会燃烧的年代","title":"在火尚未学会燃烧的年代，","level":1,"anchor":"#在火尚未学会燃烧的年代","children":[]}],"blocks":[{"type":"heading","level":1,"title":"在火尚未学会燃烧的年代，","anchor":"#在火尚未学会燃烧的年代"},{"type":"paragraph","text":"在火尚未学会燃烧的年代，\n世界第一次听见了热的声音。"},{"type":"paragraph","text":"那声音化作一束光，\n那光化作一团火，\n那火最终化作一位皇者。"},{"type":"paragraph","text":"他的名号——\n布尔玛。"},{"type":"paragraph","text":"他行走，\n空气开始枯萎。"},{"type":"paragraph","text":"他驻足，\n阴影被瞬间蒸发。"},{"type":"paragraph","text":"魔法触及他，\n不是打中，\n是被烤成灰。"},{"type":"paragraph","text":"那是抗法面纱的呼吸。\n火焰为他守卫，\n火焰以他为尊。"},{"type":"paragraph","text":"布尔玛喷吐三昧真火，\n不是法术，\n是审判。"},{"type":"paragraph","text":"火焰倾泻成河，\n天地被他随意雕刻，\n敌人像纸张般卷曲、\n撕裂、\n化尽。"},{"type":"paragraph","text":"大地被他唤醒，\n地火从深处冲破枷锁，\n如怒吼，\n如惩戒，\n如大地自己选择的报复。"},{"type":"paragraph","text":"灼烧会追击敌人，\n像一段无法熄灭的罪行记录。"},{"type":"paragraph","text":"而当真炎法皇的光辉绽开，\n火焰在他手中狂舞，\n伤害成倍暴涨，\n连魔抗都会被烧穿，\n只留下焦黑与尖叫。"},{"type":"paragraph","text":"可这仍不是他的极致。"},{"type":"paragraph","text":"当布尔玛抬头望向天穹，\n连星辰都仿佛屏息，\n等待命运的指令。"},{"type":"paragraph","text":"他的手指落下——\n天火撕裂云层，\n轰鸣如破碎的宇宙，\n光芒像一次世界性的赎罪。"},{"type":"paragraph","text":"蓄力越久，\n天火越像神祇的怒目。"},{"type":"paragraph","text":"当火球砸落，\n敌人不知是生被夺走，\n还是灵被燃尽。"},{"type":"paragraph","text":"他站在烈焰中，\n像君王，\n像灾难，\n像火焰本身的意识在世界上行走。"},{"type":"paragraph","text":"布尔玛不需要宣告。\n凡目见其焰者，"},{"type":"kv","key":"都会明白","value":""},{"type":"paragraph","text":"——火焰有了意志。\n——意志选择了皇。\n——皇降临之处，万物终将以灰烬偿还。"}],"parser":{"contentType":"text","format":"structured-text","profile":"kv-text","lineCount":80,"fieldCount":2,"blockCount":22},"parserStats":{"blockCount":22,"headingCount":1,"paragraphCount":20,"listCount":0,"tableCount":0,"kvCount":1},"rawPath":"design-data/backstory/智力/烈焰法皇.txt","raw":"在火尚未学会燃烧的年代，\n世界第一次听见了热的声音。\n\n那声音化作一束光，\n那光化作一团火，\n那火最终化作一位皇者。\n\n他的名号——\n布尔玛。\n\n他行走，\n空气开始枯萎。\n\n他驻足，\n阴影被瞬间蒸发。\n\n魔法触及他，\n不是打中，\n是被烤成灰。\n\n那是抗法面纱的呼吸。\n火焰为他守卫，\n火焰以他为尊。\n\n布尔玛喷吐三昧真火，\n不是法术，\n是审判。\n\n火焰倾泻成河，\n天地被他随意雕刻，\n敌人像纸张般卷曲、\n撕裂、\n化尽。\n\n大地被他唤醒，\n地火从深处冲破枷锁，\n如怒吼，\n如惩戒，\n如大地自己选择的报复。\n\n灼烧会追击敌人，\n像一段无法熄灭的罪行记录。\n\n而当真炎法皇的光辉绽开，\n火焰在他手中狂舞，\n伤害成倍暴涨，\n连魔抗都会被烧穿，\n只留下焦黑与尖叫。\n\n可这仍不是他的极致。\n\n当布尔玛抬头望向天穹，\n连星辰都仿佛屏息，\n等待命运的指令。\n\n他的手指落下——\n天火撕裂云层，\n轰鸣如破碎的宇宙，\n光芒像一次世界性的赎罪。\n\n蓄力越久，\n天火越像神祇的怒目。\n\n当火球砸落，\n敌人不知是生被夺走，\n还是灵被燃尽。\n\n他站在烈焰中，\n像君王，\n像灾难，\n像火焰本身的意识在世界上行走。\n\n布尔玛不需要宣告。\n凡目见其焰者，\n都会明白：\n\n——火焰有了意志。\n——意志选择了皇。\n——皇降临之处，万物终将以灰烬偿还。\n"}}
