{"schemaVersion":"standard-doc-v1","source":{"path":"design-data/design-heros/智力/真菌怪灵","extension":"","size":1731,"modifiedAt":"2026-06-18T10:32:05.339Z"},"meta":{"title":"真菌怪灵","category":"hero","group":"英雄 / 智力","attribute":"智力","hero":"真菌怪灵"},"parser":{"contentType":"text","format":"structured-text","lineCount":76},"fields":{"攻击类型":"远程","攻击距离":"400","基础攻击间隔":"1.55","基础移动速度":"300","主属性":"智力","力量":"20 + 2.4","敏捷":"19 + 2.3","智力":"25 + 3","天生技能":"菌丝遍布\n玛尔沙的移动会留下敌人无法察觉的踪迹菌丝，\n该踪迹会有200宽度的视野滞留，菌丝持续35s","技能1":"孢子迸发\n玛尔沙不断向周围释放孢子\n孢子会治疗周围的友方单位\n单位越少，治疗效果越好","范围":"400","基础治疗量每秒":"40/60/80/100","每多一个单位分享降低":"20","最低治疗":"20","持续时间":["8","4","1.5/2/2.5/3","3/4/5"],"冷却":["20/19/18/17","20/18/16/14","110/105/100"],"魔力消耗":["90/100/110/120","100/105/110/115","150/175/200"],"技能2":"带毒菌盖\n对玛尔沙造成伤害的敌方单位将受到持续的魔法伤害\n并且还会降低攻击力和技能伤害，可被弱驱散","伤害每秒":"16/30/44/58","攻击力降低":"10/15/20/25%","技能伤害降低":"10/15/20/25%","技能3":"缠绕菌藤\n玛尔沙缠绕住一个单位，持续造成魔法伤害\n被缠绕的单位无法攻击或者移动\n可以驱散","距离":["400","300","400"],"伤害每0.5秒":"30/40/50/60","技能4":"致幻毒素\n玛尔沙对一个敌方英雄释放致幻毒素\n使其不受控制，并且疯狂攻击\n其视野范围内周围友军\n可以驱散","目标攻击力提高":"30/45/60%","阳印":"出芽\n孢子迸发可以对友军释放，使其跟随其进行","阴印":"真丝\n菌丝遍布的持续时间+15s","铸魔":"孢子迸发的单位的分享降低仅为10点，并且范围增加100","铸神":"致幻毒素仅强驱散，并且施法距离提高150","_header":"真菌怪灵\n玛尔沙"},"sections":[{"key":"_header","value":"真菌怪灵\n玛尔沙"},{"key":"攻击类型","value":"远程"},{"key":"攻击距离","value":"400"},{"key":"基础攻击间隔","value":"1.55"},{"key":"基础移动速度","value":"300"},{"key":"主属性","value":"智力"},{"key":"力量","value":"20 + 2.4"},{"key":"敏捷","value":"19 + 2.3"},{"key":"智力","value":"25 + 3"},{"key":"天生技能","value":"菌丝遍布\n玛尔沙的移动会留下敌人无法察觉的踪迹菌丝，\n该踪迹会有200宽度的视野滞留，菌丝持续35s"},{"key":"技能1","value":"孢子迸发\n玛尔沙不断向周围释放孢子\n孢子会治疗周围的友方单位\n单位越少，治疗效果越好"},{"key":"范围","value":"400"},{"key":"基础治疗量每秒","value":"40/60/80/100"},{"key":"每多一个单位分享降低","value":"20"},{"key":"最低治疗","value":"20"},{"key":"持续时间","value":"8"},{"key":"冷却","value":"20/19/18/17"},{"key":"魔力消耗","value":"90/100/110/120"},{"key":"技能2","value":"带毒菌盖\n对玛尔沙造成伤害的敌方单位将受到持续的魔法伤害\n并且还会降低攻击力和技能伤害，可被弱驱散"},{"key":"伤害每秒","value":"16/30/44/58"},{"key":"攻击力降低","value":"10/15/20/25%"},{"key":"技能伤害降低","value":"10/15/20/25%"},{"key":"持续时间","value":"4"},{"key":"技能3","value":"缠绕菌藤\n玛尔沙缠绕住一个单位，持续造成魔法伤害\n被缠绕的单位无法攻击或者移动\n可以驱散"},{"key":"距离","value":"400"},{"key":"伤害每0.5秒","value":"30/40/50/60"},{"key":"持续时间","value":"1.5/2/2.5/3"},{"key":"冷却","value":"20/18/16/14"},{"key":"魔力消耗","value":"100/105/110/115"},{"key":"技能4","value":"致幻毒素\n玛尔沙对一个敌方英雄释放致幻毒素\n使其不受控制，并且疯狂攻击\n其视野范围内周围友军\n可以驱散"},{"key":"持续时间","value":"3/4/5"},{"key":"距离","value":"300"},{"key":"目标攻击力提高","value":"30/45/60%"},{"key":"冷却","value":"110/105/100"},{"key":"魔力消耗","value":"150/175/200"},{"key":"阳印","value":"出芽\n孢子迸发可以对友军释放，使其跟随其进行"},{"key":"距离","value":"400"},{"key":"阴印","value":"真丝\n菌丝遍布的持续时间+15s"},{"key":"铸魔","value":"孢子迸发的单位的分享降低仅为10点，并且范围增加100"},{"key":"铸神","value":"致幻毒素仅强驱散，并且施法距离提高150"}],"rawPath":"design-data/design-heros/智力/真菌怪灵","raw":"真菌怪灵\n玛尔沙\n攻击类型：远程\n攻击距离：400\n基础攻击间隔：1.55\n基础移动速度：300\n主属性：智力\n力量：20 + 2.4\n敏捷：19 + 2.3\n智力：25 + 3\n\n天生技能：\n菌丝遍布\n玛尔沙的移动会留下敌人无法察觉的踪迹菌丝，\n该踪迹会有200宽度的视野滞留，菌丝持续35s\n\n技能1：\n孢子迸发\n玛尔沙不断向周围释放孢子\n孢子会治疗周围的友方单位\n单位越少，治疗效果越好\n范围：400\n基础治疗量每秒：40/60/80/100\n每多一个单位分享降低：20\n最低治疗：20\n持续时间：8\n冷却：20/19/18/17\n魔力消耗：90/100/110/120\n\n技能2：\n带毒菌盖\n对玛尔沙造成伤害的敌方单位将受到持续的魔法伤害\n并且还会降低攻击力和技能伤害，可被弱驱散\n伤害每秒：16/30/44/58\n攻击力降低：10/15/20/25%\n技能伤害降低：10/15/20/25%\n持续时间：4\n\n技能3：\n缠绕菌藤\n玛尔沙缠绕住一个单位，持续造成魔法伤害\n被缠绕的单位无法攻击或者移动\n可以驱散\n距离：400\n伤害每0.5秒：30/40/50/60\n持续时间：1.5/2/2.5/3\n冷却：20/18/16/14\n魔力消耗：100/105/110/115\n\n技能4：\n致幻毒素\n玛尔沙对一个敌方英雄释放致幻毒素\n使其不受控制，并且疯狂攻击\n其视野范围内周围友军\n可以驱散\n持续时间：3/4/5\n距离：300\n目标攻击力提高：30/45/60%\n冷却：110/105/100\n魔力消耗：150/175/200\n\n阳印：\n出芽\n孢子迸发可以对友军释放，使其跟随其进行\n距离：400\n\n阴印：\n真丝\n菌丝遍布的持续时间+15s\n\n铸魔：\n孢子迸发的单位的分享降低仅为10点，并且范围增加100\n\n铸神：\n致幻毒素仅强驱散，并且施法距离提高150\n"}
