{"schemaVersion":"standard-doc-v2","source":{"path":"design-data/design-units/势力/攻城车","extension":"","size":230,"modifiedAt":"2026-07-23T10:53:45.965Z"},"meta":{"title":"攻城车","category":"unit","group":"单位 / 势力/攻城车","purpose":"单位 / 势力"},"parser":{"contentType":"text","format":"structured-text","profile":"kv-text","lineCount":21,"fieldCount":16,"blockCount":17},"fields":{"攻击类型":"远程","生命":"800","攻击":"50","护甲":"4","魔抗":"30%","回血":"","攻击间隔":"2","攻击距离":"550","攻击范围":"","移动速度":"280","状态抗性":"","击杀奖励":"80","被动":"","主动":"","技能":"","_header":"攻城车"},"sections":[{"key":"_header","value":"攻城车"},{"key":"段落","value":"攻城车"},{"key":"攻击类型","value":"远程"},{"key":"生命","value":"800"},{"key":"攻击","value":"50"},{"key":"护甲","value":"4"},{"key":"魔抗","value":"30%"},{"key":"回血","value":""},{"key":"攻击间隔","value":"2"},{"key":"攻击距离","value":"550"},{"key":"攻击范围","value":""},{"key":"移动速度","value":"280"},{"key":"状态抗性","value":""},{"key":"击杀奖励","value":"80"},{"key":"被动","value":""},{"key":"主动","value":""},{"key":"技能","value":""}],"blocks":[{"type":"heading","level":1,"title":"攻城车","anchor":"#攻城车"},{"type":"paragraph","text":"攻城车"},{"type":"kv","key":"攻击类型","value":"远程"},{"type":"kv","key":"生命","value":"800"},{"type":"kv","key":"攻击","value":"50"},{"type":"kv","key":"护甲","value":"4"},{"type":"kv","key":"魔抗","value":"30%"},{"type":"kv","key":"回血","value":""},{"type":"kv","key":"攻击间隔","value":"2"},{"type":"kv","key":"攻击距离","value":"550"},{"type":"kv","key":"攻击范围","value":""},{"type":"kv","key":"移动速度","value":"280"},{"type":"kv","key":"状态抗性","value":""},{"type":"kv","key":"击杀奖励","value":"80"},{"type":"kv","key":"被动","value":""},{"type":"kv","key":"主动","value":""},{"type":"kv","key":"技能","value":""}],"outline":[{"id":"攻城车","title":"攻城车","level":1,"anchor":"#攻城车","children":[]}],"parserStats":{"blockCount":17,"headingCount":1,"paragraphCount":1,"listCount":0,"tableCount":0,"kvCount":15},"rawPath":"design-data/design-units/势力/攻城车","raw":"攻城车\n\n攻击类型：远程\n生命：800\n攻击：50\n护甲：4\n魔抗：30%\n回血：\n攻击间隔：2\n攻击距离：550\n攻击范围：\n移动速度：280\n状态抗性：\n击杀奖励：80\n\n被动：\n\n主动：\n\n技能：\n"}
